setup.py
easy_ml/Binomialdistribution.py
easy_ml/Gaussiandistribution.py
easy_ml/Generaldistribution.py
easy_ml/__init__.py
easy_ml.egg-info/PKG-INFO
easy_ml.egg-info/SOURCES.txt
easy_ml.egg-info/dependency_links.txt
easy_ml.egg-info/not-zip-safe
easy_ml.egg-info/top_level.txt