Metadata-Version: 1.0
Name: easy-ml
Version: 0.1
Summary: Easy way to use ML Distributions
Home-page: UNKNOWN
Author: Sparsh Srivastava
Author-email: mailtosparshsri@gmail.com
License: UNKNOWN
Platform: UNKNOWN
